streamlit_image_gallery/__init__.py
streamlit_image_gallery/example.py
streamlit_image_gallery/frontend/build/asset-manifest.json
streamlit_image_gallery/frontend/build/bootstrap.min.css
streamlit_image_gallery/frontend/build/index.html
streamlit_image_gallery/frontend/build/static/js/main.2a63623e.js
streamlit_image_gallery/frontend/build/static/js/main.2a63623e.js.LICENSE.txt
streamlit_image_gallery/frontend/build/static/js/main.2a63623e.js.map
streamlit_image_gallery-0.0.2.dist-info/LICENSE
streamlit_image_gallery-0.0.2.dist-info/METADATA
streamlit_image_gallery-0.0.2.dist-info/WHEEL
streamlit_image_gallery-0.0.2.dist-info/top_level.txt
streamlit_image_gallery-0.0.2.dist-info/RECORD
