Metadata-Version: 2.1
Name: streamlit-image-gallery
Version: 0.0.2
Summary: Streamlit component for displaying multiple images in a grid
Home-page: https://github.com/virtUOS/streamlit-image-gallery
Author: Dennis Benz
Author-email: debenz@uni-osnabrueck.de
License: UNKNOWN
Platform: UNKNOWN
Requires-Python: >=3.7
License-File: LICENSE
Requires-Dist: streamlit (>=0.63)
Provides-Extra: devel
Requires-Dist: playwright (==1.39.0) ; extra == 'devel'
Requires-Dist: pytest-playwright-snapshot (==1.0) ; extra == 'devel'
Requires-Dist: pytest-rerunfailures (==12.0) ; extra == 'devel'
Requires-Dist: pytest (==7.4.0) ; extra == 'devel'
Requires-Dist: requests (==2.31.0) ; extra == 'devel'
Requires-Dist: wheel ; extra == 'devel'
